remote_fs-0.1.7.dist-info/dependency_links.txt
remote_fs-0.1.7.dist-info/entry_points.txt
remote_fs-0.1.7.dist-info/METADATA
remote_fs-0.1.7.dist-info/top_level.txt
remote_fs-0.1.7.dist-info/WHEEL
remote_fs/sshfs.py
remote_fs/fs_config.py
remote_fs/__init__.py
remote_fs/smbfs.py
remote_fs/fs.py
remote_fs/fs_abc.py
remote_fs/cli/__init__.py
remote_fs/cli/aliases.py
remote_fs/cli/cli.py
remote_fs/cli/settings.py
remote_fs/cli/ctx.py
remote_fs-0.1.7.dist-info/RECORD